{
  "main": {
    "id": "a1a8b3c542ed5632",
    "type": "split",
    "children": [
      {
        "id": "df8cf4ef02ecd2bb",
        "type": "tabs",
        "children": [
          {
            "id": "5e6d0a18a391bb6c",
            "type": "leaf",
            "state": {
              "type": "empty",
              "state": {}
            }
          }
        ]
      }
    ],
    "direction": "vertical"
  },
  "left": {
    "id": "30cd864c528f4ae8",
    "type": "split",
    "children": [
      {
        "id": "8950d3cbd66202eb",
        "type": "tabs",
        "children": [
          {
            "id": "395512c90bed7004",
            "type": "leaf",
            "state": {
              "type": "file-explorer",
              "state": {
                "sortOrder": "alphabetical"
              }
            }
          },
          {
            "id": "e0711838d40d34fb",
            "type": "leaf",
            "state": {
              "type": "search",
              "state": {
                "query": "",
                "matchingCase": false,
                "explainSearch": false,
                "collapseAll": false,
                "extraContext": false,
                "sortOrder": "alphabetical"
              }
            }
          },
          {
            "id": "afaf79d075bc5c38",
            "type": "leaf",
            "state": {
              "type": "bookmarks",
              "state": {}
            }
          }
        ]
      }
    ],
    "direction": "horizontal",
    "width": 300
  },
  "right": {
    "id": "4e092122bd41b9e1",
    "type": "split",
    "children": [
      {
        "id": "437b9bbc590b7735",
        "type": "tabs",
        "children": [
          {
            "id": "a8aa46c820ae977c",
            "type": "leaf",
            "state": {
              "type": "backlink",
              "state": {
                "file": "2024-06-06.md",
                "collapseAll": false,
                "extraContext": false,
                "sortOrder": "alphabetical",
                "showSearch": false,
                "searchQuery": "",
                "backlinkCollapsed": false,
                "unlinkedCollapsed": true
              }
            }
          },
          {
            "id": "b952586e5ad63bed",
            "type": "leaf",
            "state": {
              "type": "outgoing-link",
              "state": {
                "file": "2024-06-06.md",
                "linksCollapsed": false,
                "unlinkedCollapsed": true
              }
            }
          },
          {
            "id": "ee2198abef84cc65",
            "type": "leaf",
            "state": {
              "type": "tag",
              "state": {
                "sortOrder": "frequency",
                "useHierarchy": true
              }
            }
          },
          {
            "id": "97d94a3addcd94b5",
            "type": "leaf",
            "state": {
              "type": "outline",
              "state": {
                "file": "2024-06-06.md"
              }
            }
          }
        ]
      }
    ],
    "direction": "horizontal",
    "width": 300,
    "collapsed": true
  },
  "left-ribbon": {
    "hiddenItems": {
      "obsidian-projects:Open projects": false,
      "obsidian-excalidraw-plugin:Create new drawing": false,
      "excel:Create Excel File": false,
      "switcher:Open quick switcher": false,
      "graph:Open graph view": false,
      "canvas:Create new canvas": false,
      "daily-notes:Open today's daily note": false,
      "templates:Insert template": false,
      "command-palette:Open command palette": false
    }
  },
  "active": "395512c90bed7004",
  "lastOpenFiles": []
}